LICENSE
README.md
setup.py
cbmi_utils/__init__.py
cbmi_utils.egg-info/PKG-INFO
cbmi_utils.egg-info/SOURCES.txt
cbmi_utils.egg-info/dependency_links.txt
cbmi_utils.egg-info/requires.txt
cbmi_utils.egg-info/top_level.txt
cbmi_utils/pytorch/__init__.py
cbmi_utils/pytorch/layers.py
cbmi_utils/pytorch/normalizations.py
cbmi_utils/pytorch/paddings.py
cbmi_utils/pytorch/transformations.py
cbmi_utils/pytorch/datasets/__init__.py
cbmi_utils/pytorch/datasets/bach.py
cbmi_utils/pytorch/datasets/colossal.py
cbmi_utils/pytorch/datasets/crush.py
cbmi_utils/pytorch/datasets/h5_dataset.py
cbmi_utils/pytorch/datasets/icpr.py
cbmi_utils/pytorch/datasets/kather.py
cbmi_utils/pytorch/datasets/lizard.py
cbmi_utils/pytorch/datasets/mai_patch.py
cbmi_utils/pytorch/datasets/midog.py
cbmi_utils/pytorch/datasets/pcam.py
cbmi_utils/pytorch/datasets/tcga.py
cbmi_utils/pytorch/datasets/vgh_nki.py
cbmi_utils/pytorch/datasets/wsss4luad.py
cbmi_utils/pytorch/hooks/__init__.py
cbmi_utils/pytorch/hooks/embedding_saver.py
cbmi_utils/pytorch/losses/__init__.py
cbmi_utils/pytorch/losses/gan_loss.py
cbmi_utils/pytorch/metrics/__init__.py
cbmi_utils/pytorch/metrics/fid.py
cbmi_utils/pytorch/models/__init__.py
cbmi_utils/pytorch/models/paws_resnet.py
cbmi_utils/pytorch/models/wide_resnet.py
cbmi_utils/pytorch/optim/__init__.py
cbmi_utils/pytorch/optim/larc.py
cbmi_utils/pytorch/tools/__init__.py
cbmi_utils/pytorch/tools/logging.py
cbmi_utils/pytorch/tools/visualizations.py
cbmi_utils/pytorch/tools/visualizations_plotly.py