Metadata-Version: 2.1
Name: cbmi-utils
Version: 0.3.33
Summary: Utility package for common features at CBMI
Home-page: https://git.tools.f4.htw-berlin.de/baumapa/cbmi_utils
Author: Patrick Baumann
Author-email: Patrick.Baumann@htw-berlin.de
License: UNKNOWN
Platform: UNKNOWN
Classifier: Programming Language :: Python :: 3
Classifier: License :: OSI Approved :: MIT License
Classifier: Operating System :: OS Independent
Requires-Python: >=3.7
License-File: LICENSE
